llm_cmd_comp_qwen/__init__.py
llm_cmd_comp_qwen/plugin.py
llm_cmd_comp_qwen-0.0.1.dist-info/licenses/LICENSE
llm_cmd_comp_qwen-0.0.1.dist-info/METADATA
llm_cmd_comp_qwen-0.0.1.dist-info/WHEEL
llm_cmd_comp_qwen-0.0.1.dist-info/entry_points.txt
llm_cmd_comp_qwen-0.0.1.dist-info/top_level.txt
llm_cmd_comp_qwen-0.0.1.dist-info/RECORD
