Metadata-Version: 2.4
Name: llm-cmd-comp-qwen
Version: 0.0.1
Summary: Use LLM to generate commands for your shell: specialized for qwen3
Author: Ryan Patterson, Zach Mueller
License: Apache-2.0
Project-URL: Homepage, https://github.com/muellerzr/llm-cmd-comp-qwen
Project-URL: Changelog, https://github.com/muellerzr/llm-cmd-comp-qwen/releases
Project-URL: Issues, https://github.com/muellerzr/llm-cmd-comp-qwen/issues
Classifier: License :: OSI Approved :: Apache Software License
License-File: LICENSE
Requires-Dist: llm
Requires-Dist: prompt_toolkit>=3.0.43
Dynamic: license-file
